[
  {
    "id": "local-afro-house",
    "title": "AFRO HOUSE",
    "artist": null,
    "genre": null,
    "audio_path": "/AFRO HOUSE.mp3",
    "mime": "audio/mpeg"
  },
  {
    "id": "local-afro-latino",
    "title": "Afro Latino",
    "artist": null,
    "genre": null,
    "audio_path": "/Afro Latino.mp3",
    "mime": "audio/mpeg"
  },
  {
    "id": "local-mix-cumbia-2026",
    "title": "MIX CUMBIA 2026",
    "artist": null,
    "genre": null,
    "audio_path": "/MIX CUMBIA 2026.mp3",
    "mime": "audio/mpeg"
  },
  {
    "id": "local-reggaeton-viejo-mix",
    "title": "Reggaeton Viejo Mix",
    "artist": null,
    "genre": null,
    "audio_path": "/Reggaeton Viejo Mix.mp3",
    "mime": "audio/mpeg"
  },
  {
    "id": "local-rufus-du-sol",
    "title": "RUFUS DU SOL",
    "artist": null,
    "genre": null,
    "audio_path": "/RUFUS DU SOL.mp3",
    "mime": "audio/mpeg"
  }
]
